{"Pic01":"pictures\\shayanRanjbarTest.png","name":"","time":0,"blackPic":"pictures\\nopic.png","gamename":["1","2","3","4","5","6","7","8","9","10","11","12"],"settingitemIdforgame":[30,50,70,150,120,100,30,200,370,390,480],"selectedGames":[0,1,2,3,4,5,4],"bAsketname":["1","2","3","4","5","6","7","8","9","10","11","12"],"basketTime":[120,120,120,120,120,120,120,120,120,120,120,120],"startplaygametime":[2500,2500,2500,2500,2500,2500,2500,2500,2500],"timeGameq":20,"timeGameFinal":50,"timerFixstop":50,"file_address":{},"speed1234":["اول","دوم","سوم","چهارم"],"currentQtime":0,"currentAnsweredTime":0,"currentansweredTotal":0,"participants":[{"active":false,"pic":"S:\\Gwork\\need\\mahan1392-07-01.jpg","name":["ماهان","رنجبر","1384","هشتم محصل","تهران"],"pointTotalx1000":0,"current_timex100":0,"current_selection":0,"current_changedAnswer":0,"current_pointx1000":0,"current_Speed1234":0,"answer":[],"points":[]},{"active":false,"pic":"C:\\Users\\Shayan\\Pictures\\82958471-fencing-logo.jpg","name":["عباس ","شمشیر","3","4","5"],"pointTotalx1000":0,"current_timex100":0,"current_selection":0,"current_changedAnswer":0,"current_pointx1000":0,"current_Speed1234":0,"answer":[],"points":[]},{"active":false,"pic":"C:\\Users\\Shayan\\Pictures\\vushu\\05.JPG","name":["محمد","2","3","4","5"],"pointTotalx1000":0,"current_timex100":0,"current_selection":0,"current_changedAnswer":0,"current_pointx1000":0,"current_Speed1234":0,"answer":[],"points":[]},{"active":false,"pic":"C:\\Users\\Shayan\\Pictures\\ss3.jpg","name":["شایان","رنجبر","1352","مهندس ردی","قائمشهر"],"pointTotalx1000":0,"current_timex100":0,"current_selection":0,"current_changedAnswer":0,"current_pointx1000":0,"current_Speed1234":0,"answer":[],"points":[]},{"active":false,"pic":"S:\\Gwork\\need\\baREaX.png","name":["نام","نام خانوادگی","متولد","تحصیلات","شهر"],"pointTotalx1000":0,"current_timex100":-1,"current_selection":0,"current_changedAnswer":0,"current_pointx1000":0,"current_Speed1234":0},{"active":false,"pic":"C:\\work\\Estekan\\pictures\\shayan.JPG","name":["نام","سرعت عمل","انتخاب چند","امتیاز جاری ","امتیاز نهایی"],"pointTotalx1000":0,"current_timex100":0,"current_selection":0,"current_changedAnswer":0,"current_pointx1000":0,"current_Speed1234":0}],"ParticipantCount":0,"Prizes":["1","2","3","4","5","6","7","8","9"],"qAllbasket":[[{"question":"سوال نونه","goz0":"سوال است","goz1":"گزینه یک","goz2":"کزینه دو","goz3":"گزینه  چهار","goz4":"گزینه  چهار","pic":"pictures\\nopic.png","correct_goz":3,"time":100,"used":true},{"question":"شاید اینبار بیایید شاید\nاگر نیامد چه شود چه نشود\nس","goz0":"سوال است","goz1":"Shayanشا  سس","goz2":"سس shayan شش hh123","goz3":"ahsasانسانیت","goz4":"٠١٢٣٤٥٦٧٨٩ش","pic":"pictures\\nopic.png","correct_goz":3,"time":81,"used":true}],[{"question":"سوال نونه","goz0":"سوال است","goz1":"گزینه یک","goz2":"کزینه دو","goz3":"گزینه  چهار","goz4":"گزینه  چهار","pic":"pictures\\nopic.png","correct_goz":2,"time":0,"used":false}],[{"question":"سوال نونه","goz0":"سوال است","goz1":"گزینه یک","goz2":"کزینه دو","goz3":"گزینه  چهار","goz4":"گزینه  چهار","pic":"pictures\\nopic.png","correct_goz":2,"time":0,"used":false}],[{"question":"سوال نونه","goz0":"سوال است","goz1":"گزینه یک","goz2":"کزینه دو","goz3":"گزینه  چهار","goz4":"گزینه  چهار","pic":"pictures\\nopic.png","correct_goz":2,"time":0,"used":false}],[{"question":"سوال نونه","goz0":"سوال است","goz1":"گزینه یک","goz2":"کزینه دو","goz3":"گزینه  چهار","goz4":"گزینه  چهار","pic":"pictures\\nopic.png","correct_goz":2,"time":0,"used":false}],[{"question":"سوال نونه","goz0":"سوال است","goz1":"گزینه یک","goz2":"کزینه دو","goz3":"گزینه  چهار","goz4":"گزینه  چهار","pic":"pictures\\nopic.png","correct_goz":2,"time":0,"used":false}],[{"question":"سوال نونه","goz0":"سوال است","goz1":"گزینه یک","goz2":"کزینه دو","goz3":"گزینه  چهار","goz4":"گزینه  چهار","pic":"pictures\\nopic.png","correct_goz":2,"time":0,"used":false}],[{"question":"سوال نونه","goz0":"سوال است","goz1":"گزینه یک","goz2":"کزینه دو","goz3":"گزینه  چهار","goz4":"گزینه  چهار","pic":"pictures\\nopic.png","correct_goz":2,"time":0,"used":false}],[{"question":"سوال نونه","goz0":"سوال است","goz1":"گزینه یک","goz2":"کزینه دو","goz3":"گزینه  چهار","goz4":"گزینه  چهار","pic":"pictures\\nopic.png","correct_goz":2,"time":0,"used":false}],[{"question":"سوال نونه","goz0":"سوال است","goz1":"گزینه یک","goz2":"کزینه دو","goz3":"گزینه  چهار","goz4":"گزینه  چهار","pic":"pictures\\nopic.png","correct_goz":2,"time":0,"used":false}],[{"question":"سوال نونه","goz0":"سوال است","goz1":"گزینه یک","goz2":"کزینه دو","goz3":"گزینه  چهار","goz4":"گزینه  چهار","pic":"pictures\\nopic.png","correct_goz":2,"time":0,"used":false}],[{"question":"سوال نونه","goz0":"سوال است","goz1":"گزینه یک","goz2":"کزینه دو","goz3":"گزینه  چهار","goz4":"گزینه  چهار","pic":"pictures\\nopic.png","correct_goz":2,"time":0,"used":false}]],"games":[{"gameid":0,"gamename":"1"},{"gameid":1,"gamename":"2"},{"gameid":2,"gamename":"3"},{"gameid":3,"gamename":"4"},{"gameid":4,"gamename":"5"},{"gameid":5,"gamename":"6"},{"gameid":6,"gamename":"7"},{"gameid":7,"gamename":"8"},{"gameid":8,"gamename":"9"},{"gameid":9,"gamename":"10"},{"gameid":10,"gamename":"11"},{"gameid":11,"gamename":"12"}],"speed1234Com":0,"qcharSendPic":"pictures\\Character\\temp\\temp.jpg"}